Classfile /C:/projects/Java_Projects/decompiler/build/classes/java/main/com/wade/decompiler/test/Test6.class
  Last modified Apr 5, 2021; size 1812 bytes
  SHA-256 checksum bce98658557195c07ee9c47cb504697066aaaab8854b86642a305abc53f5a8c7
  Compiled from "Test6.java"
public class com.wade.decompiler.test.Test6
  minor version: 0
  major version: 59
  flags: (0x0021) ACC_PUBLIC, ACC_SUPER
  this_class: #11                         // com/wade/decompiler/test/Test6
  super_class: #2                         // java/lang/Object
  interfaces: 0, fields: 1, methods: 3, attributes: 3
Constant pool:
   #1 = Methodref          #2.#3          // java/lang/Object."<init>":()V
   #2 = Class              #4             // java/lang/Object
   #3 = NameAndType        #5:#6          // "<init>":()V
   #4 = Utf8               java/lang/Object
   #5 = Utf8               <init>
   #6 = Utf8               ()V
   #7 = Class              #8             // java/util/ArrayList
   #8 = Utf8               java/util/ArrayList
   #9 = Methodref          #7.#3          // java/util/ArrayList."<init>":()V
  #10 = Fieldref           #11.#12        // com/wade/decompiler/test/Test6.value:Ljava/util/List;
  #11 = Class              #13            // com/wade/decompiler/test/Test6
  #12 = NameAndType        #14:#15        // value:Ljava/util/List;
  #13 = Utf8               com/wade/decompiler/test/Test6
  #14 = Utf8               value
  #15 = Utf8               Ljava/util/List;
  #16 = String             #17            // Red
  #17 = Utf8               Red
  #18 = String             #19            // Green
  #19 = Utf8               Green
  #20 = String             #21            // Blue
  #21 = Utf8               Blue
  #22 = InterfaceMethodref #23.#24        // java/util/List.of:(Ljava/lang/Object;Ljava/lang/Object;Ljava/lang/Object;)Ljava/util/List;
  #23 = Class              #25            // java/util/List
  #24 = NameAndType        #26:#27        // of:(Ljava/lang/Object;Ljava/lang/Object;Ljava/lang/Object;)Ljava/util/List;
  #25 = Utf8               java/util/List
  #26 = Utf8               of
  #27 = Utf8               (Ljava/lang/Object;Ljava/lang/Object;Ljava/lang/Object;)Ljava/util/List;
  #28 = InterfaceMethodref #23.#29        // java/util/List.stream:()Ljava/util/stream/Stream;
  #29 = NameAndType        #30:#31        // stream:()Ljava/util/stream/Stream;
  #30 = Utf8               stream
  #31 = Utf8               ()Ljava/util/stream/Stream;
  #32 = InvokeDynamic      #0:#33         // #0:test:()Ljava/util/function/Predicate;
  #33 = NameAndType        #34:#35        // test:()Ljava/util/function/Predicate;
  #34 = Utf8               test
  #35 = Utf8               ()Ljava/util/function/Predicate;
  #36 = InterfaceMethodref #37.#38        // java/util/stream/Stream.filter:(Ljava/util/function/Predicate;)Ljava/util/stream/Stream;
  #37 = Class              #39            // java/util/stream/Stream
  #38 = NameAndType        #40:#41        // filter:(Ljava/util/function/Predicate;)Ljava/util/stream/Stream;
  #39 = Utf8               java/util/stream/Stream
  #40 = Utf8               filter
  #41 = Utf8               (Ljava/util/function/Predicate;)Ljava/util/stream/Stream;
  #42 = InterfaceMethodref #37.#43        // java/util/stream/Stream.count:()J
  #43 = NameAndType        #44:#45        // count:()J
  #44 = Utf8               count
  #45 = Utf8               ()J
  #46 = Methodref          #47.#48        // java/lang/String.length:()I
  #47 = Class              #49            // java/lang/String
  #48 = NameAndType        #50:#51        // length:()I
  #49 = Utf8               java/lang/String
  #50 = Utf8               length
  #51 = Utf8               ()I
  #52 = Utf8               Signature
  #53 = Utf8               Ljava/util/List<Ljava/lang/String;>;
  #54 = Utf8               Code
  #55 = Utf8               LineNumberTable
  #56 = Utf8               LocalVariableTable
  #57 = Utf8               this
  #58 = Utf8               Lcom/wade/decompiler/test/Test6;
  #59 = Utf8               numberOfLongColorNames
  #60 = Utf8               Ljava/util/stream/Stream;
  #61 = Utf8               LocalVariableTypeTable
  #62 = Utf8               Ljava/util/stream/Stream<Ljava/lang/String;>;
  #63 = Utf8               lambda$numberOfLongColorNames$0
  #64 = Utf8               (Ljava/lang/String;)Z
  #65 = Utf8               c
  #66 = Utf8               Ljava/lang/String;
  #67 = Utf8               StackMapTable
  #68 = Utf8               SourceFile
  #69 = Utf8               Test6.java
  #70 = Utf8               BootstrapMethods
  #71 = MethodHandle       6:#72          // REF_invokeStatic java/lang/invoke/LambdaMetafactory.metafactory:(Ljava/lang/invoke/MethodHandles$Lookup;Ljava/lang/String;Ljava/lang/invoke/MethodType;Ljava/lang/invoke/MethodType;Ljava/lang/invoke/MethodHandle;Ljava/lang/invoke/MethodType;)Ljava/lang/invoke/CallSite;
  #72 = Methodref          #73.#74        // java/lang/invoke/LambdaMetafactory.metafactory:(Ljava/lang/invoke/MethodHandles$Lookup;Ljava/lang/String;Ljava/lang/invoke/MethodType;Ljava/lang/invoke/MethodType;Ljava/lang/invoke/MethodHandle;Ljava/lang/invoke/MethodType;)Ljava/lang/invoke/CallSite;
  #73 = Class              #75            // java/lang/invoke/LambdaMetafactory
  #74 = NameAndType        #76:#77        // metafactory:(Ljava/lang/invoke/MethodHandles$Lookup;Ljava/lang/String;Ljava/lang/invoke/MethodType;Ljava/lang/invoke/MethodType;Ljava/lang/invoke/MethodHandle;Ljava/lang/invoke/MethodType;)Ljava/lang/invoke/CallSite;
  #75 = Utf8               java/lang/invoke/LambdaMetafactory
  #76 = Utf8               metafactory
  #77 = Utf8               (Ljava/lang/invoke/MethodHandles$Lookup;Ljava/lang/String;Ljava/lang/invoke/MethodType;Ljava/lang/invoke/MethodType;Ljava/lang/invoke/MethodHandle;Ljava/lang/invoke/MethodType;)Ljava/lang/invoke/CallSite;
  #78 = MethodType         #79            //  (Ljava/lang/Object;)Z
  #79 = Utf8               (Ljava/lang/Object;)Z
  #80 = MethodHandle       6:#81          // REF_invokeStatic com/wade/decompiler/test/Test6.lambda$numberOfLongColorNames$0:(Ljava/lang/String;)Z
  #81 = Methodref          #11.#82        // com/wade/decompiler/test/Test6.lambda$numberOfLongColorNames$0:(Ljava/lang/String;)Z
  #82 = NameAndType        #63:#64        // lambda$numberOfLongColorNames$0:(Ljava/lang/String;)Z
  #83 = MethodType         #64            //  (Ljava/lang/String;)Z
  #84 = Utf8               InnerClasses
  #85 = Class              #86            // java/lang/invoke/MethodHandles$Lookup
  #86 = Utf8               java/lang/invoke/MethodHandles$Lookup
  #87 = Class              #88            // java/lang/invoke/MethodHandles
  #88 = Utf8               java/lang/invoke/MethodHandles
  #89 = Utf8               Lookup
{
  java.util.List<java.lang.String> value;
    descriptor: Ljava/util/List;
    flags: (0x0000)
    Signature: #53                          // Ljava/util/List<Ljava/lang/String;>;

  public com.wade.decompiler.test.Test6();
    descriptor: ()V
    flags: (0x0001) ACC_PUBLIC
    Code:
      stack=3, locals=1, args_size=1
         0: aload_0
         1: invokespecial #1                  // Method java/lang/Object."<init>":()V
         4: aload_0
         5: new           #7                  // class java/util/ArrayList
         8: dup
         9: invokespecial #9                  // Method java/util/ArrayList."<init>":()V
        12: putfield      #10                 // Field value:Ljava/util/List;
        15: return
      LineNumberTable:
        line 7: 0
        line 8: 4
      LocalVariableTable:
        Start  Length  Slot  Name   Signature
            0      16     0  this   Lcom/wade/decompiler/test/Test6;

  public long numberOfLongColorNames();
    descriptor: ()J
    flags: (0x0001) ACC_PUBLIC
    Code:
      stack=3, locals=4, args_size=1
         0: ldc           #16                 // String Red
         2: ldc           #18                 // String Green
         4: ldc           #20                 // String Blue
         6: invokestatic  #22                 // InterfaceMethod java/util/List.of:(Ljava/lang/Object;Ljava/lang/Object;Ljava/lang/Object;)Ljava/util/List;
         9: astore_1
        10: aload_1
        11: invokeinterface #28,  1           // InterfaceMethod java/util/List.stream:()Ljava/util/stream/Stream;
        16: astore_2
        17: aload_2
        18: invokedynamic #32,  0             // InvokeDynamic #0:test:()Ljava/util/function/Predicate;
        23: invokeinterface #36,  2           // InterfaceMethod java/util/stream/Stream.filter:(Ljava/util/function/Predicate;)Ljava/util/stream/Stream;
        28: astore_3
        29: aload_3
        30: invokeinterface #42,  1           // InterfaceMethod java/util/stream/Stream.count:()J
        35: lreturn
      LineNumberTable:
        line 11: 0
        line 12: 10
        line 13: 17
        line 14: 29
      LocalVariableTable:
        Start  Length  Slot  Name   Signature
            0      36     0  this   Lcom/wade/decompiler/test/Test6;
           10      26     1 value   Ljava/util/List;
           17      19     2 stream   Ljava/util/stream/Stream;
           29       7     3 filter   Ljava/util/stream/Stream;
      LocalVariableTypeTable:
        Start  Length  Slot  Name   Signature
           10      26     1 value   Ljava/util/List<Ljava/lang/String;>;
           17      19     2 stream   Ljava/util/stream/Stream<Ljava/lang/String;>;
           29       7     3 filter   Ljava/util/stream/Stream<Ljava/lang/String;>;

  private static boolean lambda$numberOfLongColorNames$0(java.lang.String);
    descriptor: (Ljava/lang/String;)Z
    flags: (0x100a) ACC_PRIVATE, ACC_STATIC, ACC_SYNTHETIC
    Code:
      stack=2, locals=1, args_size=1
         0: aload_0
         1: invokevirtual #46                 // Method java/lang/String.length:()I
         4: iconst_3
         5: if_icmple     12
         8: iconst_1
         9: goto          13
        12: iconst_0
        13: ireturn
      LineNumberTable:
        line 13: 0
      LocalVariableTable:
        Start  Length  Slot  Name   Signature
            0      14     0     c   Ljava/lang/String;
      StackMapTable: number_of_entries = 2
        frame_type = 12 /* same */
        frame_type = 64 /* same_locals_1_stack_item */
          stack = [ int ]
}
SourceFile: "Test6.java"
BootstrapMethods:
  0: #71 REF_invokeStatic java/lang/invoke/LambdaMetafactory.metafactory:(Ljava/lang/invoke/MethodHandles$Lookup;Ljava/lang/String;Ljava/lang/invoke/MethodType;Ljava/lang/invoke/MethodType;Ljava/lang/invoke/MethodHandle;Ljava/lang/invoke/MethodType;)Ljava/lang/invoke/CallSite;
    Method arguments:
      #78 (Ljava/lang/Object;)Z
      #80 REF_invokeStatic com/wade/decompiler/test/Test6.lambda$numberOfLongColorNames$0:(Ljava/lang/String;)Z
      #83 (Ljava/lang/String;)Z
InnerClasses:
  public static final #89= #85 of #87;    // Lookup=class java/lang/invoke/MethodHandles$Lookup of class java/lang/invoke/MethodHandles
